Metadata-Version: 1.1
Name: py3ari
Version: 0.1.4
Summary: Library for accessing the Asterisk REST Interface
Home-page: https://github.com/jjsearle/ari-py
Author: Joe Searle
Author-email: joe@jsearle.net
License: BSD 3-Clause License
Platform: UNKNOWN
Classifier: Development Status :: 1 - Planning
Classifier: Intended Audience :: Developers
Classifier: Topic :: Software Development :: Libraries :: Python Modules
Classifier: License :: OSI Approved :: BSD License
Classifier: Operating System :: OS Independent
Classifier: Programming Language :: Python
